de/__init__.py
de/_version.py
de/de.py
de/fdc.py
de/generate_errors.py
de/kge.py
de/misc.py
de/nse.py
de/signatures.py
de/util.py
tests/__init__.py
tests/test_de.py
tests/test_fdc.py
tests/test_generate_errors.py
tests/test_kge.py
tests/test_nse.py
tests/test_util.py
diag_eff-1.1.dist-info/LICENSE
diag_eff-1.1.dist-info/METADATA
diag_eff-1.1.dist-info/WHEEL
diag_eff-1.1.dist-info/top_level.txt
diag_eff-1.1.dist-info/RECORD
