Metadata-Version: 2.1
Name: diag-eff
Version: 1.1
Summary: diag-eff: Diagnostic Efficiency
Home-page: https://github.com/schwemro/diag-eff
Author: Robin Schwemmle
Author-email: robin.schwemmle@hydrology.uni-freiburg.de
License: GPLv3
Platform: UNKNOWN
Classifier: Development Status :: 4 - Beta
Classifier: Intended Audience :: Science/Research
Classifier: Topic :: Scientific/Engineering :: Hydrology
Classifier: Topic :: Scientific/Engineering :: Visualization
Classifier: License :: OSI Approved :: GNU General Public License v3 (GPLv3)
Classifier: Operating System :: OS Independent
Classifier: Natural Language :: English
Classifier: Programming Language :: Python :: 3
Classifier: Programming Language :: Python :: 3.6
Classifier: Programming Language :: Python :: 3.7
Classifier: Programming Language :: Python :: 3.8
Requires-Python: >=3.6
Requires-Dist: numpy
Requires-Dist: scipy
Requires-Dist: matplotlib
Requires-Dist: seaborn
Requires-Dist: pandas
Provides-Extra: test
Requires-Dist: pytest ; extra == 'test'
Requires-Dist: coverage ; extra == 'test'
Requires-Dist: pytest-cov ; extra == 'test'
Requires-Dist: collective.checkdocs ; extra == 'test'
Requires-Dist: pygments ; extra == 'test'
Requires-Dist: numpy ; extra == 'test'
Requires-Dist: scipy ; extra == 'test'
Requires-Dist: matplotlib ; extra == 'test'
Requires-Dist: seaborn ; extra == 'test'
Requires-Dist: pandas ; extra == 'test'
